pyuscope-2.1.0.data/scripts/pyuscope-bal-gui-v4l2-mu800
pyuscope-2.1.0.data/scripts/pyuscope-bal-img
pyuscope-2.1.0.data/scripts/pyuscope-demo-auto-detect-source
pyuscope-2.1.0.data/scripts/pyuscope-demo-control-scroll
pyuscope-2.1.0.data/scripts/pyuscope-demo-full
pyuscope-2.1.0.data/scripts/pyuscope-demo-full-roi
pyuscope-2.1.0.data/scripts/pyuscope-demo-roi
pyuscope-2.1.0.data/scripts/pyuscope-demo-sink-tee
pyuscope-2.1.0.data/scripts/pyuscope-demo-tee
pyuscope-2.1.0.data/scripts/pyuscope-focus-eval
pyuscope-2.1.0.data/scripts/pyuscope-main-gui
pyuscope-2.1.0.data/scripts/pyuscope-planner-lcnc
pyuscope-2.1.0.data/scripts/pyuscope-planner-mock
pyuscope-2.1.0.data/scripts/pyuscope-prop-gui
pyuscope-2.1.0.data/scripts/pyuscope-xray-plan-cli
uscope/__init__.py
uscope/benchmark.py
uscope/config.py
uscope/control_scroll.py
uscope/control_scrolls.py
uscope/gst_util.py
uscope/gstwidget.py
uscope/img_util.py
uscope/lcnc_ar.py
uscope/ngc.py
uscope/paramiko_util.py
uscope/planner.py
uscope/temp_file.py
uscope/util.py
uscope/v4l2_util.py
uscope/hal/__init__.py
uscope/hal/cnc/__init__.py
uscope/hal/cnc/axis.py
uscope/hal/cnc/controller.py
uscope/hal/cnc/hal.py
uscope/hal/cnc/lcnc.py
uscope/hal/cnc/lcnc_ar.py
uscope/hal/cnc/mc.py
uscope/hal/cnc/mock_controller.py
uscope/hal/cnc/pr0ndexer.py
uscope/hal/cnc/pr0ndexer_controller.py
uscope/hal/img/__init__.py
uscope/hal/img/imager.py
uscope/hal/img/vcimager.py
uscope/imagers/__init__.py
uscope/imagers/gst_toupcamsrc/__init__.py
uscope/imagers/gst_toupcamsrc/widgets.py
uscope/imagers/gst_v4l2src/__init__.py
uscope/imagers/gst_v4l2src/widgets.py
uscope/imagers/gst_v4l2src_mu800/__init__.py
uscope/imagers/gst_v4l2src_mu800/widgets.py
uscope/lcnc/__init__.py
uscope/lcnc/client.py
uscope/lcnc/rsh.py
uscope/lcnc/server.py
uscope/main_gui/__init__.py
uscope/main_gui/main.py
uscope/main_gui/threads.py
pyuscope-2.1.0.dist-info/METADATA
pyuscope-2.1.0.dist-info/WHEEL
pyuscope-2.1.0.dist-info/top_level.txt
pyuscope-2.1.0.dist-info/RECORD
