Metadata-Version: 2.1
Name: pyuscope
Version: 2.1.0
Summary: Microscope panorama GUI
Home-page: https://github.com/JohnDMcMaster/pyuscope
Author: John McMaster
Author-email: JohnDMcMaster@gmail.com
License: BSD
Keywords: microscope touptek
Platform: UNKNOWN
Classifier: License :: OSI Approved :: BSD License
